MANIFEST.in
README.rst
setup.cfg
setup.py
tjango/__init__.py
tjango.egg-info/PKG-INFO
tjango.egg-info/SOURCES.txt
tjango.egg-info/dependency_links.txt
tjango.egg-info/requires.txt
tjango.egg-info/top_level.txt