Metadata-Version: 1.1
Name: tjango
Version: 0.1.0
Summary: A package to develop tornado in django style
Home-page: UNKNOWN
Author: Kido Zhang
Author-email: kidozh@kidozh.com
License: MIT License
Keywords: admin
Platform: any
Classifier: Intended Audience :: Developers
Classifier: License :: OSI Approved :: MIT License
Classifier: Programming Language :: Python :: 2
Classifier: Programming Language :: Python :: 2.6
Classifier: Programming Language :: Python :: 2.7
Classifier: Programming Language :: Python :: 3
Classifier: Programming Language :: Python :: 3.2
Classifier: Programming Language :: Python :: 3.3
Classifier: Programming Language :: Python :: 3.4
